ipy_compare/The VGER Group-share.png
ipy_compare/__init__.py
ipy_compare/brand.py
ipy_compare/panel.py
ipy_compare-0.4.1.dist-info/METADATA
ipy_compare-0.4.1.dist-info/WHEEL
ipy_compare-0.4.1.dist-info/RECORD
