Metadata-Version: 2.4
Name: ipy-compare
Version: 0.4.1
Summary: 
License: MIT
Keywords: data,analysis,visualization,pandas,ipython,panel,google-colab,jupyterlab
Author: patrick o'leary
Author-email: pjaol@pjaol.com
Requires-Python: >=3.10,<3.11
Classifier: Development Status :: 3 - Alpha
Classifier: Intended Audience :: Developers
Classifier: License :: OSI Approved :: MIT License
Classifier: Programming Language :: Python :: 3
Classifier: Programming Language :: Python :: 3.10
Classifier: Topic :: Software Development :: Libraries :: Python Modules
Requires-Dist: bokeh (>=3.8.2)
Requires-Dist: h11 (>=0.16.0)
Requires-Dist: ipython (>=8.10.0,<9.0.0)
Requires-Dist: jinja2 (>=3.1.6)
Requires-Dist: pandas (==2.2.2)
Requires-Dist: panel (>=1.3.1,<2.0.0)
Requires-Dist: requests (>=2.32.4)
Requires-Dist: setuptools (>=78.1.1)
Requires-Dist: tornado (>=6.5)
Requires-Dist: urllib3 (>=2.6.3)
Project-URL: Homepage, https://github.com/thevgergroup/ipy-compare
Project-URL: Repository, https://github.com/thevgergroup/ipy-compare
